[
  {
    "CPF": "39109000038",
    "city": "Pato Branco",
    "email": "adolfo@viasoft.com.br",
    "branch": null,
    "userId": 108190,
    "isLeader": 0,
    "leaderId": null,
    "jobRoleId": 30825,
    "situation": "inactive",
    "userGoals": [],
    "departmentId": 15025,
    "jobRoleTitle": "ADMINISTRADOR",
    "userFullName": "VIASOFT SUPORTE",
    "accessProfile": "Perfil Administrador",
    "jobFunctionId": null,
    "departmentName": "ADMINISTRACAO",
    "leaderFullName": null,
    "data de admissao": null,
    "jobFunctionTitle": null,
    "situationHistory": [],
    "data de inativacao": null
  },
  {
    "CPF": "07461288350",
    "city": "Fortaleza",
    "email": "heitor@online.net.br",
    "branch": 3134,
    "userId": 113935,
    "isLeader": 1,
    "leaderId": 115542,
    "jobRoleId": 37323,
    "situation": "active",
    "userGoals": [],
    "departmentId": 15046,
    "jobRoleTitle": "GERENTE DE LOGÍSTICA E SUPRIMENTOS",
    "userFullName": "HEITOR TELES MONTE",
    "accessProfile": "Liderança Online Telecom",
    "jobFunctionId": 41901,
    "departmentName": "DIRETORIA",
    "leaderFullName": "VALMIR BERTOLDO VIANA FILHO",
    "data de admissao": "2016-10-01",
    "jobFunctionTitle": "Avaliação de Desempenho Julho 2024",
    "situationHistory": [],
    "data de inativacao": null
  },
  {
    "CPF": "94404780710",
    "city": null,
    "email": "joia@online.net.br",
    "branch": 2389,
    "userId": 113936,
    "isLeader": 0,
    "leaderId": 115548,
    "jobRoleId": 36373,
    "situation": "active",
    "userGoals": [],
    "departmentId": 15050,
    "jobRoleTitle": "ASSISTENTE FINANCEIRO ",
    "userFullName": "FRANCISCA ARISOLANGELA TELES PEREIRA",
    "accessProfile": "Perfil Usuário Padrão",
    "jobFunctionId": 41901,
    "departmentName": "FINANCEIRO",
    "leaderFullName": "PAULO MARCELO AGUIAR FREIRE",
    "data de admissao": "2012-08-28",
    "jobFunctionTitle": "Avaliação de Desempenho Julho 2024",
    "situationHistory": [],
    "data de inativacao": null
  }
]